{
  "version": "7",
  "dialect": "mysql",
  "entries": [
    {
      "idx": 0,
      "version": "5",
      "when": 1753774491538,
      "tag": "0000_youthful_katie_power",
      "breakpoints": true
    },
    {
      "idx": 1,
      "version": "5",
      "when": 1753778227361,
      "tag": "0001_mighty_kulan_gath",
      "breakpoints": true
    },
    {
      "idx": 2,
      "version": "5",
      "when": 1753786792799,
      "tag": "0002_fast_oracle",
      "breakpoints": true
    },
    {
      "idx": 3,
      "version": "5",
      "when": 1753860864813,
      "tag": "0003_dry_layla_miller",
      "breakpoints": true
    },
    {
      "idx": 4,
      "version": "5",
      "when": 1753938628988,
      "tag": "0004_woozy_oracle",
      "breakpoints": true
    },
    {
      "idx": 5,
      "version": "5",
      "when": 1753944485429,
      "tag": "0005_red_cobalt_man",
      "breakpoints": true
    },
    {
      "idx": 6,
      "version": "5",
      "when": 1754032365297,
      "tag": "0006_vengeful_iron_monger",
      "breakpoints": true
    }
  ]
}